funkagent/__init__.py
funkagent/agents.py
funkagent/parser.py
funkagent-0.0.3.dist-info/WHEEL
funkagent-0.0.3.dist-info/METADATA
funkagent-0.0.3.dist-info/RECORD
